README.md
setup.py
uds
uds/__init__.py
uds/cli.py
uds.egg-info/PKG-INFO
uds.egg-info/SOURCES.txt
uds.egg-info/dependency_links.txt
uds.egg-info/entry_points.txt
uds.egg-info/requires.txt
uds.egg-info/top_level.txt