Metadata-Version: 2.1
Name: uds
Version: 0.1.9
Summary: Dictionary CLI searcher: supports Urban, Cambridge
Home-page: https://github.com/hvnsweeting/uds
Author: Viet Hung Nguyen
Author-email: hvn@familug.org
License: MIT
Platform: UNKNOWN
Classifier: Environment :: Console
